src/__init__.py
src/sympycalc.py
sympycalc-1.0.1.dist-info/DESCRIPTION.rst
sympycalc-1.0.1.dist-info/METADATA
sympycalc-1.0.1.dist-info/RECORD
sympycalc-1.0.1.dist-info/WHEEL
sympycalc-1.0.1.dist-info/entry_points.txt
sympycalc-1.0.1.dist-info/metadata.json
sympycalc-1.0.1.dist-info/top_level.txt
